setup.py
tdjango/__init__.py
tdjango/adapter.py
tdjango/db.py
tdjango.egg-info/PKG-INFO
tdjango.egg-info/SOURCES.txt
tdjango.egg-info/dependency_links.txt
tdjango.egg-info/requires.txt
tdjango.egg-info/top_level.txt
tdjango/tests/__init__.py
tdjango/tests/test_django.py
tdjango/tests/testapp/__init__.py
tdjango/tests/testapp/models.py
tdjango/tests/testapp/settings.py
tdjango/tests/testapp/migrations/0001_initial.py
tdjango/tests/testapp/migrations/0002_auto_20151125_1850.py
tdjango/tests/testapp/migrations/0003_rainbows_name.py
tdjango/tests/testapp/migrations/__init__.py