Metadata-Version: 1.1
Name: tdjango
Version: 0.0.2
Summary: A Twisted interface to the Django ORM
Home-page: http://github.com/calston/tdjango
Author: Colin Alston
Author-email: colin.alston@gmail.com
License: MIT
Platform: UNKNOWN
Classifier: Development Status :: 4 - Beta
Classifier: License :: OSI Approved :: MIT License
Classifier: Operating System :: POSIX
Classifier: Programming Language :: Python
